tornado_directmail/__init__.py
tornado_directmail/client.py
tornado_directmail/test.py
tornado_directmail_aliyun-1.0.2.dist-info/DESCRIPTION.rst
tornado_directmail_aliyun-1.0.2.dist-info/METADATA
tornado_directmail_aliyun-1.0.2.dist-info/RECORD
tornado_directmail_aliyun-1.0.2.dist-info/WHEEL
tornado_directmail_aliyun-1.0.2.dist-info/metadata.json
tornado_directmail_aliyun-1.0.2.dist-info/top_level.txt
