Metadata-Version: 2.0
Name: tornado-directmail-aliyun
Version: 1.0.2
Summary: aliyun directmail sdk
Home-page: https://github.com/haozi3156666/tornado-ali-directmail.git
Author: haolee
Author-email: haolee1990@qq.com
License: MIT Licence
Keywords: pip,aliyun,tornado,directmail
Platform: any
